browsez/__init__.py
browsez/__main__.py
browsez/api_client.py
browsez/check_tool.py
browsez/cli.py
browsez/config.py
browsez/packaging.py
browsez/schemas.py
browsez/upload_tool.py
browsez_cli-0.1.0.dist-info/METADATA
browsez_cli-0.1.0.dist-info/WHEEL
browsez_cli-0.1.0.dist-info/entry_points.txt
browsez_cli-0.1.0.dist-info/top_level.txt
browsez_cli-0.1.0.dist-info/RECORD
