Metadata-Version: 2.4
Name: browsez-cli
Version: 0.1.0
Summary: CLI tool for publishing tools and UI modules to the BrowsEZ platform
Author: Bryan Abraham
License: MIT
Project-URL: Homepage, https://github.com/browsez/cli
Project-URL: Documentation, https://github.com/browsez/cli#readme
Project-URL: Repository, https://github.com/browsez/cli
Keywords: browsez,cli,tools,publishing
Classifier: Development Status :: 4 - Beta
Classifier: Environment :: Console
Classifier: Intended Audience :: Developers
Classifier: License :: OSI Approved :: MIT License
Classifier: Operating System :: OS Independent
Classifier: Programming Language :: Python :: 3
Classifier: Programming Language :: Python :: 3.9
Classifier: Programming Language :: Python :: 3.10
Classifier: Programming Language :: Python :: 3.11
Classifier: Programming Language :: Python :: 3.12
Classifier: Topic :: Software Development :: Build Tools
Requires-Python: >=3.9
Requires-Dist: click>=8.0.0
Requires-Dist: requests>=2.31.0
Requires-Dist: pydantic>=2.0.0
Requires-Dist: PyYAML>=6.0
Provides-Extra: dev
Requires-Dist: types-PyYAML; extra == "dev"
Requires-Dist: types-requests; extra == "dev"
Requires-Dist: build; extra == "dev"
Requires-Dist: twine; extra == "dev"
